{
  "project_info": {
    "project_number": "1093883503160",
    "project_id": "apeiron-bio",
    "storage_bucket": "apeiron-bio.appspot.com"
  },
  "client": [
    {
      "client_info": {
        "mobilesdk_app_id": "1:1093883503160:android:9636de44e218425099fccd",
        "android_client_info": {
          "package_name": "bio.apeiron.chat"
        }
      },
      "oauth_client": [
        {
          "client_id": "1093883503160-vnm43fa7ohp8osp6astj5c4itft5cqlu.apps.googleusercontent.com",
          "client_type": 1,
          "android_info": {
            "package_name": "bio.apeiron.chat",
            "certificate_hash": "9bbb3186b2189ef16d8f272bdab59362c395cbb4"
          }
        },
        {
          "client_id": "1093883503160-ss4jhmn4sn2bomurft96hb74nqghb4rq.apps.googleusercontent.com",
          "client_type": 3
        }
      ],
      "api_key": [
        {
          "current_key": "AIzaSyCQMPjm3CZuSYTgcJPU0FTu2gpiMVePeDo"
        }
      ],
      "services": {
        "appinvite_service": {
          "other_platform_oauth_client": [
            {
              "client_id": "1093883503160-olg55ih3fjbhur7fbjhsut3ntaup59nc.apps.googleusercontent.com",
              "client_type": 3
            },
            {
              "client_id": "1093883503160-8ej7v24209jektlac40u391hptfioar3.apps.googleusercontent.com",
              "client_type": 2,
              "ios_info": {
                "bundle_id": "bio.apeiron.chat"
              }
            }
          ]
        }
      }
    }
  ],
  "configuration_version": "1"
}